odoo10_addon_users_ldap_mail-10.0.1.0.0-py2.7-nspkg.pth
odoo10_addon_users_ldap_mail-10.0.1.0.0.dist-info/top_level.txt
odoo10_addon_users_ldap_mail-10.0.1.0.0.dist-info/WHEEL
odoo10_addon_users_ldap_mail-10.0.1.0.0.dist-info/RECORD
odoo10_addon_users_ldap_mail-10.0.1.0.0.dist-info/metadata.json
odoo10_addon_users_ldap_mail-10.0.1.0.0.dist-info/DESCRIPTION.rst
odoo10_addon_users_ldap_mail-10.0.1.0.0.dist-info/METADATA
odoo10_addon_users_ldap_mail-10.0.1.0.0.dist-info/namespace_packages.txt
odoo/addons/users_ldap_mail/__manifest__.py
odoo/addons/users_ldap_mail/__init__.py
odoo/addons/users_ldap_mail/README.rst
odoo/addons/users_ldap_mail/models/users_ldap_model.py
odoo/addons/users_ldap_mail/models/__init__.py
odoo/addons/users_ldap_mail/i18n/zh_CN.po
odoo/addons/users_ldap_mail/i18n/es.po
odoo/addons/users_ldap_mail/i18n/users_ldap_mail.pot
odoo/addons/users_ldap_mail/i18n/sl.po
odoo/addons/users_ldap_mail/i18n/de.po
odoo/addons/users_ldap_mail/i18n/fr.po
odoo/addons/users_ldap_mail/i18n/pt_BR.po
odoo/addons/users_ldap_mail/i18n/hr_HR.po
odoo/addons/users_ldap_mail/views/users_ldap_view.xml
odoo/addons/users_ldap_mail/static/description/icon.png
